passwordrd/__init__.py
passwordrd/modulo.py
passwordrd-0.1.0.dist-info/licenses/LICENSE
passwordrd-0.1.0.dist-info/METADATA
passwordrd-0.1.0.dist-info/WHEEL
passwordrd-0.1.0.dist-info/top_level.txt
passwordrd-0.1.0.dist-info/RECORD
