Metadata-Version: 2.4
Name: passwordrd
Version: 0.1.0
Summary: Executa eval() com senha e mensagens de erro detalhadas
Home-page: https://github.com/seu_usuario/passwordrd
Author: Seu Nome
Author-email: seu.email@example.com
Classifier: Programming Language :: Python :: 3
Classifier: License :: OSI Approved :: MIT License
Classifier: Operating System :: OS Independent
Requires-Python: >=3.6
License-File: LICENSE
Dynamic: author
Dynamic: author-email
Dynamic: classifier
Dynamic: description-content-type
Dynamic: home-page
Dynamic: license-file
Dynamic: requires-python
Dynamic: summary
